vlm_ocr/__init__.py
vlm_ocr/readers.py
vlm_ocr-0.1.41.dist-info/METADATA
vlm_ocr-0.1.41.dist-info/WHEEL
vlm_ocr-0.1.41.dist-info/top_level.txt
vlm_ocr-0.1.41.dist-info/RECORD
